<?xml version="1.0"?>
<!DOCTYPE hibernate-mapping PUBLIC "-//Hibernate/Hibernate Mapping DTD 3.0//EN"
"http://hibernate.sourceforge.net/hibernate-mapping-3.0.dtd">
<!-- Generated 23-lug-2009 0.07.34 by Hibernate Tools 3.2.4.GA -->
<hibernate-mapping>
    <class name="it.infolabs.hibernate.GiacenzaArticoliAllView" table="giacenza_articoli_all_view" schema="public">
        <composite-id name="id" class="it.infolabs.hibernate.GiacenzaArticoliAllViewId">
            <key-property name="idarticolo" type="java.lang.Long">
                <column name="idarticolo" />
            </key-property>
            <key-property name="codice" type="string">
                <column name="codice" length="40" />
            </key-property>
            <key-property name="descrizione" type="string">
                <column name="descrizione" length="100" />
            </key-property>
            <key-property name="um" type="string">
                <column name="um" length="40" />
            </key-property>
            <key-property name="carico" type="java.lang.Double">
                <column name="carico" precision="17" scale="17" />
            </key-property>
            <key-property name="scarico" type="java.lang.Double">
                <column name="scarico" precision="17" scale="17" />
            </key-property>
            <key-property name="deposito" type="java.lang.Double">
                <column name="deposito" precision="17" scale="17" />
            </key-property>
            <key-property name="prezzoAcquisto" type="java.lang.Double">
                <column name="prezzo_acquisto" precision="17" scale="17" />
            </key-property>
            <key-property name="prezzoTot" type="java.lang.Double">
                <column name="prezzo_tot" precision="17" scale="17" />
            </key-property>
        </composite-id>
    </class>
</hibernate-mapping>
